bioflex/__init__.py
bioflex/_base_object.py
bioflex/_connection.py
bioflex/_database.py
bioflex/_metadata.py
bioflex/_study.py
bioflex/common.py
bioflex/connection.py
bioflex/constants.py
bioflex/database.py
bioflex/metadata.py
bioflex/study.py
bioflex-1.2.0.dist-info/LICENSE
bioflex-1.2.0.dist-info/METADATA
bioflex-1.2.0.dist-info/WHEEL
bioflex-1.2.0.dist-info/top_level.txt
bioflex-1.2.0.dist-info/RECORD
