Metadata-Version: 2.1
Name: bioflex
Version: 1.2.0
Summary: A set of python modules for accessing BioTuring single-cell database
Author-email: BioTuring developers <support@bioturing.com>
License: MIT
Project-URL: Homepage, https://datascience.bioturing.com/
Project-URL: Bug Tracker, https://github.com/bioturing/bioflex/issues
Classifier: Programming Language :: Python :: 3
Classifier: License :: OSI Approved :: MIT License
Classifier: Operating System :: OS Independent
Requires-Python: >=3.7
License-File: LICENSE
Requires-Dist: requests
Requires-Dist: numpy
Requires-Dist: scipy
Requires-Dist: tqdm
Requires-Dist: h5py
